dpk_blocklist/__init__.py
dpk_blocklist/local.py
dpk_blocklist/runtime.py
dpk_blocklist/transform.py
dpk_blocklist/ray/__init__.py
dpk_blocklist/ray/local.py
dpk_blocklist/ray/runtime.py
dpk_blocklist/ray/s3.py
dpk_bloom/__init__.py
dpk_bloom/local.py
dpk_bloom/local_python.py
dpk_bloom/transform.py
dpk_bloom/transform_python.py
dpk_code2parquet/__init__.py
dpk_code2parquet/local.py
dpk_code2parquet/local_python.py
dpk_code2parquet/runtime.py
dpk_code2parquet/transform.py
dpk_code2parquet/ray/__init__.py
dpk_code2parquet/ray/runtime.py
dpk_code_profiler/UAST.py
dpk_code_profiler/UAST_parser.py
dpk_code_profiler/__init__.py
dpk_code_profiler/higher_order_concepts.py
dpk_code_profiler/local.py
dpk_code_profiler/local_python.py
dpk_code_profiler/output_data-prep-kit.sl.cloud9.ibm.com_20250129-062407-115.html
dpk_code_profiler/output_data-prep-kit.sl.cloud9.ibm.com_20250129-062407-115.json
dpk_code_profiler/profiler_report.py
dpk_code_profiler/semantic_concepts.py
dpk_code_profiler/template.html
dpk_code_profiler/transform.py
dpk_code_profiler/transform_python.py
dpk_code_profiler/data/helper.ipynb
dpk_code_profiler/data/Concept_dataset/uast_comment/agda/0.txt
dpk_code_profiler/data/Concept_dataset/uast_comment/c/0.txt
dpk_code_profiler/data/Concept_dataset/uast_comment/c_sharp/0.txt
dpk_code_profiler/data/Concept_dataset/uast_comment/cpp/0.txt
dpk_code_profiler/data/Concept_dataset/uast_comment/d/0.txt
dpk_code_profiler/data/Concept_dataset/uast_comment/dart/0.txt
dpk_code_profiler/data/Concept_dataset/uast_comment/dart/1.txt
dpk_code_profiler/data/Concept_dataset/uast_comment/elm/0.txt
dpk_code_profiler/data/Concept_dataset/uast_comment/elm/1.txt
dpk_code_profiler/data/Concept_dataset/uast_comment/go/0.txt
dpk_code_profiler/data/Concept_dataset/uast_comment/haskell/0.txt
dpk_code_profiler/data/Concept_dataset/uast_comment/java/0.txt
dpk_code_profiler/data/Concept_dataset/uast_comment/java/1.txt
dpk_code_profiler/data/Concept_dataset/uast_comment/js/0.txt
data_prep_toolkit_transforms-1.1.6.dist-info/METADATA
data_prep_toolkit_transforms-1.1.6.dist-info/WHEEL
data_prep_toolkit_transforms-1.1.6.dist-info/top_level.txt
data_prep_toolkit_transforms-1.1.6.dist-info/RECORD
